comfy_uiapi/__init__.py
comfy_uiapi/client.py
comfy_uiapi/model_defs.py
comfy_uiapi-0.1.0.dist-info/METADATA
comfy_uiapi-0.1.0.dist-info/WHEEL
comfy_uiapi-0.1.0.dist-info/RECORD
