Metadata-Version: 2.4
Name: comfy-uiapi
Version: 0.1.0
Summary: Python client for ComfyUI-uiapi - programmatic control of ComfyUI workflows
Project-URL: Homepage, https://github.com/holo-q/comfy-uiapi-client
Project-URL: Repository, https://github.com/holo-q/comfy-uiapi-client
Author: holo-q
License-Expression: MIT
Keywords: api,client,comfyui,image-generation,stable-diffusion
Classifier: Development Status :: 4 - Beta
Classifier: Intended Audience :: Developers
Classifier: License :: OSI Approved :: MIT License
Classifier: Programming Language :: Python :: 3.11
Classifier: Programming Language :: Python :: 3.12
Classifier: Topic :: Multimedia :: Graphics
Requires-Python: >=3.11
Requires-Dist: aiofiles>=24.1
Requires-Dist: httpx>=0.27
Requires-Dist: numpy>=1.26
Requires-Dist: opencv-python>=4.9
Requires-Dist: pillow>=10.0
Requires-Dist: websockets>=13.0
Provides-Extra: dev
Requires-Dist: pytest; extra == 'dev'
Requires-Dist: pytest-asyncio; extra == 'dev'
Requires-Dist: ruff; extra == 'dev'
